constants.py
linearalgebra.py
misc.py
systems.py
ndn4sid-0.0.12.dist-info/LICENSE.txt
ndn4sid-0.0.12.dist-info/METADATA
ndn4sid-0.0.12.dist-info/WHEEL
ndn4sid-0.0.12.dist-info/top_level.txt
ndn4sid-0.0.12.dist-info/RECORD
