Metadata-Version: 2.1
Name: ndn4sid
Version: 0.0.12
Summary: A package to perform n4sid on nD systems
Home-page: https://example.com
Author: Bob Vergauwen
Author-email: bob.vergauwen@gmail.com
License: UNKNOWN
Platform: UNKNOWN
Classifier: Programming Language :: Python :: 3.7
Classifier: Programming Language :: Python :: 3.8
Classifier: Programming Language :: Python :: 3.9
Classifier: License :: OSI Approved :: MIT License
Classifier: Operating System :: OS Independent
Requires-Dist: numpy (~=1.19)
Requires-Dist: sympy (~=1.6.2)
Provides-Extra: dev
Requires-Dist: pytest (~=3.7) ; extra == 'dev'
Requires-Dist: check-manifest (~=0.46) ; extra == 'dev'
Requires-Dist: twine (~=3.4.2) ; extra == 'dev'
Requires-Dist: tox (~=3.24) ; extra == 'dev'
